{
  "id": "d430874d-e439-4bfd-a1d2-53e621440fa2",
  "name": "Mojaloop PI3.5 Local K8s on Docker",
  "values": [
    {
      "key": "payeefsp",
      "value": "dfsp2",
      "description": {
        "content": "",
        "type": "text/plain"
      },
      "enabled": true
    },
    {
      "key": "payerfsp",
      "value": "dfsp1",
      "description": {
        "content": "",
        "type": "text/plain"
      },
      "enabled": true
    },
    {
      "key": "transferId",
      "value": "d3b3c1b2-86db-4814-bc6e-b5f5c853e331",
      "description": {
        "content": "",
        "type": "text/plain"
      },
      "enabled": true
    },
    {
      "key": "transferExpiration",
      "value": "2018-11-08T21:31:00.534+01:00",
      "description": {
        "content": "",
        "type": "text/plain"
      },
      "enabled": true
    },
    {
      "key": "transactionRequestId",
      "value": "25a00155-c777-4629-a6b7-61cf0d16f499",
      "enabled": true
    },
    {
      "key": "transferDate",
      "value": "2018-09-07",
      "enabled": true
    },
    {
      "key": "currentTimestamp",
      "value": "2018-09-07T09:50:39.482Z",
      "enabled": true
    },
    {
      "key": "participant",
      "value": "payerfsp",
      "enabled": true
    },
    {
      "key": "participantProxyURL",
      "value": "",
      "description": {
        "content": "",
        "type": "text/plain"
      },
      "enabled": true
    },
    {
      "key": "quoteDate",
      "value": "2018-08-22",
      "enabled": true
    },
    {
      "key": "quoteId",
      "value": "b75e6b83-87b2-4895-bcac-c9ab8f3b72ab",
      "enabled": true
    },
    {
      "key": "quoteExpiration",
      "value": "2018-11-08T21:31:00.534+01:00",
      "description": {
        "content": "",
        "type": "text/plain"
      },
      "enabled": true
    },
    {
      "key": "partiesType",
      "value": "MSISDN",
      "description": {
        "content": "",
        "type": "text/plain"
      },
      "enabled": true
    },
    {
      "key": "partyId",
      "value": "27713803910",
      "description": {
        "content": "",
        "type": "text/plain"
      },
      "enabled": true
    },
    {
      "key": "partyDate",
      "value": "2018-08-22",
      "description": {
        "content": "",
        "type": "text/plain"
      },
      "enabled": true
    },
    {
      "key": "HOST_MOJALOOP",
      "value": "interop-switch.local",
      "description": {
        "content": "",
        "type": "text/plain"
      },
      "enabled": true
    },
    {
      "key": "BASE_MOJALOOP",
      "value": "/interop/switch/v1",
      "description": {
        "content": "",
        "type": "text/plain"
      },
      "enabled": true
    },
    {
      "key": "HOST_CENTRAL_LEDGER",
      "value": "central-ledger.local",
      "description": {
        "content": "",
        "type": "text/plain"
      },
      "enabled": true
    },
    {
      "key": "BASE_CENTRAL_LEDGER_API",
      "value": "",
      "description": {
        "content": "",
        "type": "text/plain"
      },
      "enabled": true
    },
    {
      "key": "BASE_CENTRAL_LEDGER_ADMIN",
      "value": "/admin",
      "description": {
        "content": "",
        "type": "text/plain"
      },
      "enabled": true
    },
    {
      "key": "HOST_INTEROP_SWITCH",
      "value": "interop-switch.local",
      "description": {
        "content": "",
        "type": "text/plain"
      },
      "enabled": true
    },
    {
      "key": "BASE_INTEROP_SWITCH",
      "value": "/interop/switch/v1",
      "description": {
        "content": "",
        "type": "text/plain"
      },
      "enabled": true
    },
    {
      "key": "HOST_ML_API",
      "value": "ml-api-adapter.local",
      "description": {
        "content": "",
        "type": "text/plain"
      },
      "enabled": true
    },
    {
      "key": "BASE_ML_API",
      "value": "",
      "description": {
        "content": "",
        "type": "text/plain"
      },
      "enabled": true
    },
    {
      "key": "HOST_CENTRAL_SETTLEMENT",
      "value": "central-settlement.local",
      "description": {
        "content": "",
        "type": "text/plain"
      },
      "enabled": true
    },
    {
      "key": "BASE_CENTRAL_SETTLEMENT",
      "value": "",
      "description": {
        "content": "",
        "type": "text/plain"
      },
      "enabled": true
    },
    {
      "key": "HOST_CENTRAL_DIRECTORY",
      "value": "central-directory.local",
      "description": {
        "content": "",
        "type": "text/plain"
      },
      "enabled": true
    },
    {
      "key": "BASE_CENTRAL_DIRECTORY",
      "value": "",
      "description": {
        "content": "",
        "type": "text/plain"
      },
      "enabled": true
    },
    {
      "key": "CONFIG_GENERATE_NEW_TRANSFER_UUID_ON_PREPARE",
      "value": "true",
      "description": {
        "content": "",
        "type": "text/plain"
      },
      "enabled": true
    },
    {
      "key": "CONFIG_GENERATE_NEW_TRANSFER_UUID_ON_QUOTE\n",
      "value": "true",
      "description": {
        "content": "",
        "type": "text/plain"
      },
      "enabled": true
    },
    {
      "key": "CONFIG_GENERATE_NEW_QUOTE_UUID_ON_QUOTE",
      "value": "true",
      "description": {
        "content": "",
        "type": "text/plain"
      },
      "enabled": true
    },
    {
      "key": "CONFIG_GENERATE_NEW_TIMESTAMP",
      "value": "true",
      "description": {
        "content": "",
        "type": "text/plain"
      },
      "enabled": true
    },
    {
      "key": "CONFIG_GENERATE_NEW_PREPARE_DATE",
      "value": "true",
      "description": {
        "content": "",
        "type": "text/plain"
      },
      "enabled": true
    },
    {
      "key": "CONFIG_GENERATE_NEW_QUOTE_DATE",
      "value": "true",
      "description": {
        "content": "",
        "type": "text/plain"
      },
      "enabled": true
    },
    {
      "key": "CONFIG_GENERATE_NEW_TRANSACTION_UUID_ON_QUOTE",
      "value": "true",
      "description": {
        "content": "",
        "type": "text/plain"
      },
      "enabled": true
    },
    {
      "key": "transferExpiredExpiration",
      "value": "2018-08-31T15:26:01.870Z",
      "enabled": true
    },
    {
      "key": "condition",
      "value": "otTwY9oJKLBrWmLI4h0FEw4ksdZtoAkX3qOVAygUlTI",
      "description": {
        "content": "",
        "type": "text/plain"
      },
      "enabled": true
    },
    {
      "key": "fulfilment",
      "value": "uU0nuZNNPgilLlLX2n2r-sSE7-N6U4DukIj3rOLvzek",
      "description": {
        "content": "",
        "type": "text/plain"
      },
      "enabled": true
    },
    {
      "key": "HOST_FSPSIM",
      "value": "",
      "type": "text",
      "description": "",
      "enabled": true
    }
  ],
  "_postman_variable_scope": "environment",
  "_postman_exported_at": "2018-09-28T15:31:49.351Z",
  "_postman_exported_using": "Postman/6.3.0"
}